estar/Declustering.py
estar/__init__.py
estar/binarisation_methods.py
estar/spatial_methods.py
estar/utils.py
estar/validation_tools.py
Estar-5.8.dist-info/METADATA
Estar-5.8.dist-info/WHEEL
Estar-5.8.dist-info/top_level.txt
Estar-5.8.dist-info/RECORD
