Metadata-Version: 2.1
Name: Estar
Version: 5.8
Requires-Dist: numpy==1.26.4
Requires-Dist: matplotlib
Requires-Dist: scikit-learn
Requires-Dist: tiffile
Requires-Dist: Pillow
Requires-Dist: scipy
Requires-Dist: scikit-image
Requires-Dist: rasterio
Requires-Dist: pyproj
Requires-Dist: pandas
Requires-Dist: shapely
Requires-Dist: geopandas
Requires-Dist: networkx
Requires-Dist: python-louvain
